vfaf/__init__.py
vfaf/vfaf.py
vfaf-0.1.0.dist-info/WHEEL
vfaf-0.1.0.dist-info/METADATA
vfaf-0.1.0.dist-info/RECORD
