Metadata-Version: 2.1
Name: vfaf
Version: 0.1.0
Summary: 
Author: Javier Daza
Author-email: javierjdaza@gmail.com
Requires-Python: >=3.8,<4.0
Classifier: Programming Language :: Python :: 3
Classifier: Programming Language :: Python :: 3.10
Classifier: Programming Language :: Python :: 3.8
Classifier: Programming Language :: Python :: 3.9
Requires-Dist: matplotlib (>=3.5.2,<4.0.0)
Requires-Dist: numpy (>=1.23.1,<2.0.0)
Requires-Dist: pandas (>=1.4.3,<2.0.0)
Requires-Dist: seaborn (>=0.11.2,<0.12.0)
